hsds_data_tool/__init__.py
hsds_data_tool/build_schema.py
hsds_data_tool/cli.py
hsds_data_tool/hsds_schemas.py
hsds_data_tool-0.1a0.dist-info/LICENSE
hsds_data_tool-0.1a0.dist-info/METADATA
hsds_data_tool-0.1a0.dist-info/WHEEL
hsds_data_tool-0.1a0.dist-info/entry_points.txt
hsds_data_tool-0.1a0.dist-info/top_level.txt
hsds_data_tool-0.1a0.dist-info/RECORD
