Metadata-Version: 2.1
Name: hsds-data-tool
Version: 0.1a0
Summary: Data validator and transformer for Human Services Data Specification.
Home-page: https://github.com/chekos/hsds-data-tool
Author: Sergio Sanchez
License: Apache License, Version 2.0
Project-URL: Issues, https://github.com/chekos/hsds-data-tool/issues
Project-URL: CI, https://github.com/chekos/hsds-data-tool/actions
Project-URL: Changelog, https://github.com/chekos/hsds-data-tool/releases
Platform: UNKNOWN
Requires-Python: >=3.7
License-File: LICENSE
Requires-Dist: typer (==0.4.0)
Requires-Dist: pandera[hypotheses] (==0.9.0)
Requires-Dist: rich (>=11.0.0)
Requires-Dist: importlib-resources (>=1.1.0) ; python_version < "3.9"
Provides-Extra: dev
Requires-Dist: black ; extra == 'dev'
Requires-Dist: jq ; extra == 'dev'
Requires-Dist: pytest (>=7.0.1) ; extra == 'dev'
Provides-Extra: test
Requires-Dist: pytest (>=7.0.1) ; extra == 'test'
